MANIFEST.in
setup.py
version.txt
spyce/__init__.py
spyce/_api.py
spyce/_compat.py
spyce/_version.py
spyce/_wrapper.py
spyce.egg-info/PKG-INFO
spyce.egg-info/SOURCES.txt
spyce.egg-info/dependency_links.txt
spyce.egg-info/not-zip-safe
spyce.egg-info/top_level.txt
spyce/__pycache__/_cffi__x368c86e1x65aaebc5.c
spyce/test/__init__.py
spyce/test/support.py
spyce/test/test_api.py
spyce/test/test_wrapper.py