Metadata-Version: 1.0
Name: spyce
Version: 0.0.20
Summary: Python CFFI bindings for FreeBSD's Capsicum sandboxing framework.
Home-page: UNKNOWN
Author: Mark Williams
Author-email: markrwilliams@gmail.com
License: UNKNOWN
Platform: UNKNOWN
